README.rst
setup.py
ham/__init__.py
ham/_version.py
ham/rules.py
ham/symbols.py
ham.egg-info/PKG-INFO
ham.egg-info/SOURCES.txt
ham.egg-info/dependency_links.txt
ham.egg-info/requires.txt
ham.egg-info/top_level.txt