Metadata-Version: 1.1
Name: ham
Version: 0.2
Summary: Tools for syllable replacement
Home-page: https://github.com/ftobia/ham
Author: Frank Tobia
Author-email: frank.tobia@gmail.com
License: MIT license
Platform: UNKNOWN
Classifier: Programming Language :: Python
Classifier: Development Status :: 3 - Alpha
Classifier: Natural Language :: English
Classifier: Intended Audience :: Developers
Classifier: License :: OSI Approved :: MIT License
Classifier: Operating System :: OS Independent
Classifier: Topic :: Software Development :: Libraries :: Python Modules
Classifier: Topic :: Text Processing :: Linguistic
